{
  "timestamp": 1763065263,
  "severity": "warning",
  "alerts": [
    "High memory usage: 252918% (threshold: 85%)"
  ],
  "system_metrics": {
    "timestamp": 1763065262,
    "cpu_usage_percent": 7.86,
    "memory_usage_percent": 252918,
    "disk_usage_percent": 14,
    "network_rx_bytes": 6002363476,
    "network_tx_bytes": 1043367250,
    "process_count": 727,
    "load_average": 1.75,
    "system_info": {
      "hostname": "MacBookPro.lan",
      "os_version": "26.2",
      "kernel_version": "25.2.0"
    }
  }
}
