{
  "timestamp": 1763068003,
  "severity": "warning",
  "alerts": [
    "High memory usage: 214179% (threshold: 85%)"
  ],
  "system_metrics": {
    "timestamp": 1763068002,
    "cpu_usage_percent": 13.70,
    "memory_usage_percent": 214179,
    "disk_usage_percent": 16,
    "network_rx_bytes": 7256701433,
    "network_tx_bytes": 1076923434,
    "process_count": 736,
    "load_average": 5.20,
    "system_info": {
      "hostname": "MacBookPro.lan",
      "os_version": "26.2",
      "kernel_version": "25.2.0"
    }
  }
}
