{
  "timestamp": 1763054214,
  "severity": "warning",
  "alerts": [
    "High memory usage: 264408% (threshold: 85%)"
  ],
  "system_metrics": {
    "timestamp": 1763054213,
    "cpu_usage_percent": 20.74,
    "memory_usage_percent": 264408,
    "disk_usage_percent": 14,
    "network_rx_bytes": 5965746863,
    "network_tx_bytes": 1000253316,
    "process_count": 751,
    "load_average": 1.95,
    "system_info": {
      "hostname": "MacBookPro.lan",
      "os_version": "26.2",
      "kernel_version": "25.2.0"
    }
  }
}
